bleuscore-0.1.6.dist-info/METADATA
bleuscore-0.1.6.dist-info/WHEEL
bleuscore/__init__.py
bleuscore/_bleuscore.abi3.so
bleuscore/py.typed
bleuscore-0.1.6.dist-info/RECORD
