Metadata-Version: 2.4
Name: bleuscore
Version: 0.1.6
Classifier: Programming Language :: Rust
Classifier: Programming Language :: Python :: Implementation :: CPython
Classifier: Programming Language :: Python :: Implementation :: PyPy
Classifier: Development Status :: 5 - Production/Stable
Classifier: Intended Audience :: Developers
Classifier: Intended Audience :: Education
Classifier: Intended Audience :: Science/Research
Classifier: Operating System :: OS Independent
Classifier: Programming Language :: Python :: 3
Classifier: Programming Language :: Python :: 3.8
Classifier: Programming Language :: Python :: 3.9
Classifier: Programming Language :: Python :: 3.10
Classifier: Programming Language :: Python :: 3.11
Classifier: Programming Language :: Python :: 3.12
Classifier: Programming Language :: Python :: 3.13
Classifier: Topic :: Scientific/Engineering :: Artificial Intelligence
Requires-Dist: pytest ; extra == 'test'
Requires-Dist: pytest-sugar ; extra == 'test'
Requires-Dist: hypothesis ; extra == 'test'
Requires-Dist: evaluate ; extra == 'test'
Requires-Dist: sacrebleu ; extra == 'test'
Requires-Dist: black ; extra == 'lint'
Requires-Dist: ruff ; extra == 'lint'
Provides-Extra: test
Provides-Extra: lint
Summary: A fast bleu score calculator
Keywords: NLP,Tokenizer,BLEU,DeepLearning
Author-email: Mathew Shen <datahonor@gmail.com>
License: MIT
Requires-Python: >=3.8
Project-URL: Homepage, https://github.com/shenxiangzhuang/bleuscore
Project-URL: Source, https://github.com/shenxiangzhuang/bleuscore
